polls/__init__.py
polls/admin.py
polls/endpoints.py
polls/models.py
polls/serializers.py
polls/urls.py
polls/views.py
polls/migrations/0001_init.py
polls/migrations/__init__.py
polls/templates/polls/poll_detail.html
polls/templates/polls/poll_list.html
polls/templates/polls/votes_panel.html
wagtail_rest_polls-0.0.2.dist-info/LICENSE
wagtail_rest_polls-0.0.2.dist-info/METADATA
wagtail_rest_polls-0.0.2.dist-info/WHEEL
wagtail_rest_polls-0.0.2.dist-info/top_level.txt
wagtail_rest_polls-0.0.2.dist-info/RECORD
