Metadata-Version: 2.1
Name: wagtail-rest-polls
Version: 0.0.2
Summary: A simple polls app for wagtail in django
Home-page: https://github.com/covalentcareers/wagtail-polls
Author: jkearney126
Author-email: josh.kearney@covalentcareers.com
License: MIT License
Platform: UNKNOWN
License-File: LICENSE
Requires-Dist: Django
